signified/__init__.py
signified/core.py
signified/display.py
signified/ops.py
signified/plugins.py
signified/py.typed
signified/types.py
signified/utils.py
signified-0.2.6.dist-info/licenses/LICENSE
signified-0.2.6.dist-info/METADATA
signified-0.2.6.dist-info/WHEEL
signified-0.2.6.dist-info/top_level.txt
signified-0.2.6.dist-info/RECORD
