Metadata-Version: 2.4
Name: signified
Version: 0.2.6
Summary: Reactive Signals and Computed values.
Author-email: Doug Mercer <dougmerceryt@gmail.com>
Maintainer-email: Doug Mercer <dougmerceryt@gmail.com>
License: BSD 3-Clause License
Project-URL: Homepage, https://github.com/dougmercer/signified.git
Project-URL: Documentation, https://dougmercer.github.io/signified
Project-URL: Repository, https://github.com/dougmercer/signified.git
Project-URL: Issues, https://github.com/dougmercer/signified/issues
Project-URL: Changelog, https://dougmercer.github.io/signified/changelog
Keywords: reactive,signals
Classifier: Development Status :: 3 - Alpha
Classifier: Programming Language :: Python
Requires-Python: >=3.9
License-File: LICENSE
Requires-Dist: pluggy
Requires-Dist: typing-extensions; python_version < "3.12"
Provides-Extra: docs
Requires-Dist: mkdocs; extra == "docs"
Requires-Dist: mkdocs-material; extra == "docs"
Requires-Dist: mkdocstrings[python]; extra == "docs"
Requires-Dist: mkdocs-material-extensions; extra == "docs"
Provides-Extra: ipython
Requires-Dist: ipython; extra == "ipython"
Dynamic: license-file
